LICENSE
MANIFEST.in
setup.cfg
setup.py
kib/__init__.py
kib/__main__.py
kib/builders.py
kib/kib.py
kib/kubeapi.py
kib/registry.py
kib/test_kubeapi.py
kib/tests.py
kib.egg-info/PKG-INFO
kib.egg-info/SOURCES.txt
kib.egg-info/dependency_links.txt
kib.egg-info/entry_points.txt
kib.egg-info/not-zip-safe
kib.egg-info/requires.txt
kib.egg-info/top_level.txt