Metadata-Version: 1.1
Name: kib
Version: 0.2
Summary: Kubernetes image builder
Home-page: https://github.com/tomkukral/kib/
Author: Tomáš Kukrál
Author-email: tomas.kukral@6shore.net
License: MIT
Download-URL: https://github.com/tomkukral/kib/archive/v0.2.tar.gz
Platform: UNKNOWN
Classifier: Operating System :: POSIX :: Linux
Classifier: Programming Language :: Python
Classifier: Programming Language :: Python :: Implementation :: CPython
Classifier: Programming Language :: Python :: 3
Classifier: Programming Language :: Python :: 3.6
